<?xml version="1.0"?>
<launch>
  <arg name="input/object" default="object"/>
  <arg name="output/long_range_object" default="long_range_object"/>
  <arg name="output/short_range_object" default="short_range_object"/>
  <arg name="param_path" default="$(find-pkg-share autoware_object_range_splitter)/config/object_range_splitter.param.yaml"/>
  <arg name="container_name" default="" description="Container name for composable node. If empty, standalone node is launched."/>

  <!-- Standalone mode: launch as a regular node when container_name is empty -->
  <node pkg="autoware_object_range_splitter" exec="object_range_splitter_node" name="object_range_splitter" output="screen" if="$(eval &quot;'$(var container_name)'==''&quot;)">
    <remap from="input/object" to="$(var input/object)"/>
    <remap from="output/long_range_object" to="$(var output/long_range_object)"/>
    <remap from="output/short_range_object" to="$(var output/short_range_object)"/>
    <param from="$(var param_path)"/>
  </node>

  <!-- Composable mode: load into existing container when container_name is specified -->
  <load_composable_node target="$(var container_name)" if="$(eval &quot;'$(var container_name)'!=''&quot;)">
    <composable_node pkg="autoware_object_range_splitter" plugin="autoware::object_range_splitter::ObjectRangeSplitterNode" name="object_range_splitter" namespace="">
      <remap from="input/object" to="$(var input/object)"/>
      <remap from="output/long_range_object" to="$(var output/long_range_object)"/>
      <remap from="output/short_range_object" to="$(var output/short_range_object)"/>
      <param from="$(var param_path)"/>
    </composable_node>
  </load_composable_node>
</launch>
